<!DOCTYPE node PUBLIC "-//freedesktop//DTD D-BUS Object Introspection 1.0//EN"
"http://www.freedesktop.org/standards/dbus/1.0/introspect.dtd">

<node>
	<interface name='org.mpris.MediaPlayer2.TrackList'>
		<method name='GetTracksMetadata'>
			<arg direction='in' name='TrackIds' type='ao' />
			<arg direction='out' name='Metadata' type='aa{sv}' />
			<annotation name="org.qtproject.QtDBus.QtTypeName.Out0" value="TrackMetadata" />
		</method>
		<method name='GetTracksMetadataString'>
			<arg direction='in' name='TrackList' type='s' />
			<arg direction='out' name='Metadata' type='aa{sv}' />
			<annotation name="org.qtproject.QtDBus.QtTypeName.Out0" value="TrackMetadata" />
		</method>
		<method name='AddTrack'>
			<arg direction='in' name='Uri' type='s' />
			<arg direction='in' name='AfterTrack' type='o' />
			<arg direction='in' name='SetAsCurrent' type='b' />
		</method>
		<method name='RemoveTrack'>
			<arg direction='in' name='TrackId' type='o' />
		</method>
		<method name='EnqueueTracks'>
			<arg direction='in' name='InsertFirst' type='b' />
			<arg direction='in' name='TrackIds' type='ao' />
		</method>
		<method name='EnqueueTracksString'>
			<arg direction='in' name='InsertFirst' type='b' />
			<arg direction='in' name='TrackList' type='s' />
		</method>
		<method name='EnqueueTracksFiltered'>
			<arg direction='in' name='InsertFirst' type='b' />
			<arg direction='in' name='Filtered' type='s' />
		</method>
		<method name='GoTo'>
			<arg direction='in' name='TrackId' type='o' />
		</method>
		<signal name='TrackListReplaced'>
			<arg name='Tracks' type='ao' />
			<arg name='CurrentTrack' type='o' />
		</signal>
		<signal name='TrackAdded'>
			<arg direction='out' name='Metadata' type='a{sv}' />
			<annotation name="org.qtproject.QtDBus.QtTypeName.Out0" value="TrackMetadata" />
			<arg name='AfterTrack' type='o' />
		</signal>
		<signal name='TrackRemoved'>
			<arg name='TrackId' type='o' />
		</signal>
		<signal name='TrackMetadataChanged'>
			<arg name='TrackId' type='o' />
			<arg direction='out' name='Metadata' type='a{sv}' />
			<annotation name="org.qtproject.QtDBus.QtTypeName.Out1" value="TrackMetadata" />
		</signal>
		<property name='Tracks' type='ao' access='read' />
		<property name='LastPlayedTracks' type='ao' access='read' />
		<method name='LastPlayedTracksString'>
			<arg direction='out' name='Metadata' type='aa{sv}' />
			<annotation name="org.qtproject.QtDBus.QtTypeName.Out0" value="TrackMetadata" />
		</method>
		<method name='FilteredTracks'>
			<arg direction='in' name='Filter' type='s' />
			<arg direction='out' name='Tracks' type='ao' />
			<annotation name="org.qtproject.QtDBus.QtTypeName.Out0" value="Track_Ids" />
		</method>
		<method name='FilteredTracksString'>
			<arg direction='in' name='Filter' type='s' />
			<arg direction='out' name='Metadata' type='aa{sv}' />
			<annotation name="org.qtproject.QtDBus.QtTypeName.Out0" value="TrackMetadata" />
		</method>
		<property name='CanEditTracks' type='b' access='read' />
	</interface>
</node>
